Workbook

Sheet Jones Model
A1: Assumptions
B2: Historical | E2: Projected
B3: 2004 | C3: 2005 | D3: 2006 | E3: 2007 | F3: =E3+1 -> 2008 | G3: =F3+1 -> 2009 | H3: =G3+1 -> 2010 | I3: =H3+1 -> 2011
A4: Sales Growth | C4: =C25/B25-1 -> 0.17980296 | D4: =D25/C25-1 -> 0.17014614 | E4: 0.2 | F4: =E4 -> 0.2 | G4: =F4 -> 0.2 | H4: =G4 -> 0.2 | I4: =H4 -> 0.2
A5: COGS/Sales | B5: =(B26-B27)/B25 -> 0.80295567 | C5: =(C26-C27)/C25 -> 0.80114823 | D5: =(D26-D27)/D25 -> 0.81088314 | E5: =D5 -> 0.81088314 | F5: =E5 -> 0.81088314 | G5: =F5 -> 0.81088314 | H5: =G5 -> 0.81088314 | I5: =H5 -> 0.81088314
A6: Operating Expenses/Sales | B6: =B30/B25 -> 0.16748768 | C6: =C30/C25 -> 0.14718163 | D6: =D30/D25 -> 0.13916146 | E6: =D6 -> 0.13916146 | F6: =E6 -> 0.13916146 | G6: =F6 -> 0.13916146 | H6: =G6 -> 0.13916146 | I6: =H6 -> 0.13916146
A7: Tax/Net Income Before Tax (tax inc<$40k) | B7: =B35/B34 -> 0.33333333 | C7: =C35/C34 -> 0.34090909 | D7: =D35/D34 -> 0.34782609 | E7: 0.3 | F7: =E7 -> 0.3 | G7: =F7 -> 0.3 | H7: =G7 -> 0.3 | I7: =H7 -> 0.3
A8: Tax/Net Income Before Tax ($40k<tax inc<$60k) | E8: 0.35 | F8: =E8 -> 0.35 | G8: =F8 -> 0.35 | H8: =G8 -> 0.35 | I8: =H8 -> 0.35
A9: Tax/Net Income Before Tax (tax inc>$60k) | E9: 0.4 | F9: =E9 -> 0.4 | G9: =F9 -> 0.4 | H9: =G9 -> 0.4 | I9: =H9 -> 0.4
A10: Int Exp Loan | E10: 0.08 | F10: =E10 -> 0.08 | G10: =F10 -> 0.08 | H10: =G10 -> 0.08 | I10: =H10 -> 0.08
A11: Int Exp New LOC | E11: 0.075 | F11: =E11 -> 0.075 | G11: =F11 -> 0.075 | H11: =G11 -> 0.075 | I11: =H11 -> 0.075
A12: Purchase Discount | B12: 0.02 | C12: 0.02 | D12: 0.02 | E12: =D12 -> 0.02 | F12: =E12 -> 0.02 | G12: =F12 -> 0.02 | H12: =G12 -> 0.02 | I12: =H12 -> 0.02
A13: Cash | B13: =B39/B25 -> 0.02770936 | C13: =C39/C25 -> 0.027661795 | D13: =D39/D25 -> 0.010258698 | E13: =D13 -> 0.010258698 | F13: =E13 -> 0.010258698 | G13: =F13 -> 0.010258698 | H13: =G13 -> 0.010258698 | I13: =H13 -> 0.010258698
A14: DSO ((A/R)/(Sales/365)) | B14: =B40/(B25/365) -> 42.028941 | C14: =C40/(C25/365) -> 44.005741 | D14: =D40/(D25/365) -> 42.979483 | E14: =D14 -> 42.979483 | F14: =E14 -> 42.979483 | G14: =F14 -> 42.979483 | H14: =G14 -> 42.979483 | I14: =H14 -> 42.979483
A15: DSI ((Inv/(COGS/365)) | B15: =B41/(B28/365) -> 68.017638 | C15: =C41/(C28/365) -> 66.104235 | D15: =D41/(D28/365) -> 76.091859 | E15: =D15 -> 76.091859 | F15: =E15 -> 76.091859 | G15: =F15 -> 76.091859 | H15: =G15 -> 76.091859 | I15: =H15 -> 76.091859
A16: Gross PPE/Sales | B16: =B43/B25 -> 0.11514778 | C16: =C43/C25 -> 0.10542797 | D16: =D43/D25 -> 0.11239964 | E16: =D16 -> 0.11239964 | F16: =E16 -> 0.11239964 | G16: =F16 -> 0.11239964 | H16: =G16 -> 0.11239964 | I16: =H16 -> 0.11239964
A17: Acc. Depr/Gross PPE | B17: =-B44/B43 -> 0.39572193 | C17: =-C44/C43 -> 0.49009901 | D17: =-D44/D43 -> 0.53174603 | E17: 0.5317 | F17: =E17 -> 0.5317 | G17: =F17 -> 0.5317 | H17: =G17 -> 0.5317 | I17: =H17 -> 0.5317
A18: DPO ((A/P)/(COGS/365)) | B18: =B49/(B28/365) -> 10.076687 | C18: =C49/(C28/365) -> 9.9869707 | D18: =D49/(D28/365) -> 24.092409 | E18: =D18 -> 24.092409 | F18: =E18 -> 24.092409 | G18: =F18 -> 24.092409 | H18: =G18 -> 24.092409 | I18: =H18 -> 24.092409
A19: Accrued Exp/Op Exp | B19: =B51/B30 -> 0.047794118 | C19: =C51/C30 -> 0.04964539 | D19: =D51/D30 -> 0.044871795 | E19: =D19 -> 0.044871795 | F19: =E19 -> 0.044871795 | G19: =F19 -> 0.044871795 | H19: =G19 -> 0.044871795 | I19: =H19 -> 0.044871795
A20: Depreciation Useful Life | E20: 15 | F20: =E20 -> 15 | G20: =F20 -> 15 | H20: =G20 -> 15 | I20: =H20 -> 15 | K20: 2006 LOC | L20: 2011 LOC
A21: Iterative Calculation for LOC (On/Off) | B21: ON | K21: =E50 -> 349.28542 | L21: =I50 -> 963.75495
A22: Income Statement
B24: 2004 | C24: 2005 | D24: 2006 | E24: 2007 | F24: =E24+1 -> 2008 | G24: =F24+1 -> 2009 | H24: =G24+1 -> 2010 | I24: =H24+1 -> 2011
A25: Net Sales | B25: 1624 | C25: 1916 | D25: 2242 | E25: =D25*(1+E4) -> 2690.4 | F25: =E25*(1+F4) -> 3228.48 | G25: =F25*(1+G4) -> 3874.176 | H25: =G25*(1+H4) -> 4649.0112 | I25: =H25*(1+I4) -> 5578.8134
A26: COGS (W/O Purchase Discount if Applicable) | B26: =IF(B18<10.1,B28/(1-B12),B28) -> 1330.6122 | C26: =IF(C18<10.1,C28/(1-C12),C28) -> 1566.3265 | D26: =IF(D18<10.1,D28/(1-D12),D28) -> 1818 | E26: =E25*E5 -> 2181.6 | F26: =F25*F5 -> 2617.92 | G26: =G25*G5 -> 3141.504 | H26: =H25*H5 -> 3769.8048 | I26: =I25*I5 -> 4523.7658
A27: Purchase Discount | B27: =IF(B18<10.1,B26*B12,0) -> 26.612245 | C27: =IF(C18<10,C26*C12,0) -> 31.326531 | D27: =IF(D18<10,D26*D12,0) -> 0 | E27: =IF(E18<10.1,E26*E12,0) -> 0 | F27: =IF(F18<10.1,F26*F12,0) -> 0 | G27: =IF(G18<10.1,G26*G12,0) -> 0 | H27: =IF(H18<10.1,H26*H12,0) -> 0 | I27: =IF(I18<10.1,I26*I12,0) -> 0
A28: Net COGS | B28: 1304 | C28: 1535 | D28: 1818 | E28: =E26-E27 -> 2181.6 | F28: =F26-F27 -> 2617.92 | G28: =G26-G27 -> 3141.504 | H28: =H26-H27 -> 3769.8048 | I28: =I26-I27 -> 4523.7658
A29: Gross Profit | B29: =B25-B28 -> 320 | C29: =C25-C28 -> 381 | D29: =D25-D28 -> 424 | E29: =E25-E28 -> 508.8 | F29: =F25-F28 -> 610.56 | G29: =G25-G28 -> 732.672 | H29: =H25-H28 -> 879.2064 | I29: =I25-I28 -> 1055.0477
A30: Operating Expense | B30: 272 | C30: =307-C31 -> 282 | D30: =347-D31 -> 312 | E30: =E25*E6 -> 374.4 | F30: =F25*F6 -> 449.28 | G30: =G25*G6 -> 539.136 | H30: =H25*H6 -> 646.9632 | I30: =I25*I6 -> 776.35584
A31: Depreciation expenses | C31: =B44-C44 -> 25 | D31: =C44-D44 -> 35 | E31: =(E43-D43)/E20+D31 -> 38.36 | F31: =(F43-E43)/F20+E31 -> 42.392 | G31: =(G43-F43)/G20+F31 -> 47.2304 | H31: =(H43-G43)/H20+G31 -> 53.03648 | I31: =(I43-H43)/I20+H31 -> 60.003776
A32: Int Exp (Loan) | B32: 27 | C32: 30 | D32: 31 | E32: =(D52+E52+D54+E54)/2*E10 -> 11.68 | F32: =(E52+F52+E54+F54)/2*F10 -> 9.76 | G32: =(F52+G52+F54+G54)/2*G10 -> 7.84 | H32: =(G52+H52+G54+H54)/2*H10 -> 5.92 | I32: =(H52+I52+H54+I54)/2*I10 -> 4
A33: Int Exp (New LOC) | E33: =E11*(D50+E50)/2 -> 22.435703 | F33: =F11*(E50+F50)/2 -> 30.608518 | G33: =G11*(F50+G50)/2 -> 40.218633 | H33: =H11*(G50+H50)/2 -> 51.562105 | I33: =I11*(H50+I50)/2 -> 64.994597
A34: Net Income before tax | B34: =B29-B30-B32 -> 21 | C34: =C29-C30-C32-C31 -> 44 | D34: =D29-D30-D32-D31 -> 46 | E34: =E29-E30-E32-E33-E31 -> 61.924297 | F34: =F29-F30-F32-F33-F31 -> 78.519482 | G34: =G29-G30-G32-G33-G31 -> 98.246967 | H34: =H29-H30-H32-H33-H31 -> 121.72462 | I34: =I29-I30-I32-I33-I31 -> 149.69347
A35: Provision for Income Tax | B35: 7 | C35: 15 | D35: 16 | E35: {=_xlfn.IFS(E34<40,E34*E7,E34<60,40*E7+(E34-40)*E8,TRUE,40*E7+(60-40)*E8+(E34-60)*E9)} -> 19.769719 | F35: {=_xlfn.IFS(F34<40,F34*F7,F34<60,40*F7+(F34-40)*F8,TRUE,40*F7+(60-40)*F8+(F34-60)*F9)} -> 26.407793 | G35: {=_xlfn.IFS(G34<40,G34*G7,G34<60,40*G7+(G34-40)*G8,TRUE,40*G7+(60-40)*G8+(G34-60)*G9)} -> 34.298787 | H35: {=_xlfn.IFS(H34<40,H34*H7,H34<60,40*H7+(H34-40)*H8,TRUE,40*H7+(60-40)*H8+(H34-60)*H9)} -> 43.689846 | I35: {=_xlfn.IFS(I34<40,I34*I7,I34<60,40*I7+(I34-40)*I8,TRUE,40*I7+(60-40)*I8+(I34-60)*I9)} -> 54.877387
A36: Net Income | B36: =B34-B35 -> 14 | C36: =C34-C35 -> 29 | D36: =D34-D35 -> 30 | E36: =E34-E35 -> 42.154578 | F36: =F34-F35 -> 52.111689 | G36: =G34-G35 -> 63.94818 | H36: =H34-H35 -> 78.034769 | I36: =I34-I35 -> 94.81608
B38: 2004 | C38: 2005 | D38: 2006 | E38: 2007 | F38: =E38+1 -> 2008 | G38: =F38+1 -> 2009 | H38: =G38+1 -> 2010 | I38: =H38+1 -> 2011
A39: Cash | B39: 45 | C39: 53 | D39: 23 | E39: =E25*E13 -> 27.6 | F39: =F25*F13 -> 33.12 | G39: =G25*G13 -> 39.744 | H39: =H25*H13 -> 47.6928 | I39: =I25*I13 -> 57.23136
A40: A/R | B40: 187 | C40: 231 | D40: 264 | E40: =E14*(E25/365) -> 316.8 | F40: =F14*(F25/365) -> 380.16 | G40: =G14*(G25/365) -> 456.192 | H40: =H14*(H25/365) -> 547.4304 | I40: =I14*(I25/365) -> 656.91648
A41: Inventory | B41: 243 | C41: 278 | D41: 379 | E41: =E15*(E28/365) -> 454.8 | F41: =F15*(F28/365) -> 545.76 | G41: =G15*(G28/365) -> 654.912 | H41: =H15*(H28/365) -> 785.8944 | I41: =I15*(I28/365) -> 943.07328
A42: Total Current Assets | B42: =SUM(B39:B41) -> 475 | C42: =SUM(C39:C41) -> 562 | D42: =SUM(D39:D41) -> 666 | E42: =SUM(E39:E41) -> 799.2 | F42: =SUM(F39:F41) -> 959.04 | G42: =SUM(G39:G41) -> 1150.848 | H42: =SUM(H39:H41) -> 1381.0176 | I42: =SUM(I39:I41) -> 1657.2211
A43: Gross PPE | B43: 187 | C43: 202 | D43: 252 | E43: =E16*E25 -> 302.4 | F43: =F16*F25 -> 362.88 | G43: =G16*G25 -> 435.456 | H43: =H16*H25 -> 522.5472 | I43: =I16*I25 -> 627.05664
A44: Accumulated Dep | B44: -74 | C44: -99 | D44: -134 | E44: =D44-E31 -> -172.36 | F44: =E44-F31 -> -214.752 | G44: =F44-G31 -> -261.9824 | H44: =G44-H31 -> -315.01888 | I44: =H44-I31 -> -375.02266
A45: Net PPE | B45: =SUM(B43:B44) -> 113 | C45: =SUM(C43:C44) -> 103 | D45: =SUM(D43:D44) -> 118 | E45: =E43+E44 -> 130.04 | F45: =F43+F44 -> 148.128 | G45: =G43+G44 -> 173.4736 | H45: =H43+H44 -> 207.52832 | I45: =I43+I44 -> 252.03398
A47: Total Assets | B47: =SUM(B45,B42) -> 588 | C47: =SUM(C45,C42) -> 665 | D47: =SUM(D45,D42) -> 784 | E47: =E45+E42 -> 929.24 | F47: =F45+F42 -> 1107.168 | G47: =G45+G42 -> 1324.3216 | H47: =H45+H42 -> 1588.5459 | I47: =I45+I42 -> 1909.2551
A49: A/P | B49: 36 | C49: 42 | D49: 120 | E49: =E18*E26/365 -> 144 | F49: =F18*F26/365 -> 172.8 | G49: =G18*G26/365 -> 207.36 | H49: =H18*H26/365 -> 248.832 | I49: =I18*I26/365 -> 298.5984
A50: Line of Credit Payable | B50: 149 | C50: 214 | D50: =249+243-D58 -> 249 | E50: =IF($B$21="on",IF(E47>(E49+E51+E52+E54+E58),E47-E49-E51-E52-E54-E58,0),0) -> 349.28542 | F50: =IF($B$21="on",IF(F47>(F49+F51+F52+F54+F58),F47-F49-F51-F52-F54-F58,0),0) -> 466.94173 | G50: =IF($B$21="on",IF(G47>(G49+G51+G52+G54+G58),G47-G49-G51-G52-G54-G58,0),0) -> 605.55515 | H50: =IF($B$21="on",IF(H47>(H49+H51+H52+H54+H58),H47-H49-H51-H52-H54-H58,0),0) -> 769.43431 | I50: =IF($B$21="on",IF(I47>(I49+I51+I52+I54+I58),I47-I49-I51-I52-I54-I58,0),0) -> 963.75495
A51: Accrued exp | B51: 13 | C51: 14 | D51: 14 | E51: =E19*E30 -> 16.8 | F51: =F19*F30 -> 20.16 | G51: =G19*G30 -> 24.192 | H51: =H19*H30 -> 29.0304 | I51: =I19*I30 -> 34.83648
A52: long term debt, current | B52: 24 | C52: 24 | D52: 24 | E52: =D52 -> 24 | F52: =E52 -> 24 | G52: =F52 -> 24 | H52: =G52 -> 24 | I52: =H52 -> 24
A53: Current Liabilities | B53: =SUM(B49:B52) -> 222 | C53: =SUM(C49:C52) -> 294 | D53: =SUM(D49:D52) -> 407 | E53: =SUM(E49:E52) -> 534.08542 | F53: =SUM(F49:F52) -> 683.90173 | G53: =SUM(G49:G52) -> 861.10715 | H53: =SUM(H49:H52) -> 1071.2967 | I53: =SUM(I49:I52) -> 1321.1898
A54: LTD | B54: 182 | C54: 158 | D54: 134 | E54: =D54-E52 -> 110 | F54: =E54-F52 -> 86 | G54: =F54-G52 -> 62 | H54: =G54-H52 -> 38 | I54: =H54-I52 -> 14
A56: Total Liabilities | B56: =SUM(B54,B53) -> 404 | C56: =SUM(C54,C53) -> 452 | D56: =SUM(D54,D53) -> 541 | E56: =E54+E53 -> 644.08542 | F56: =F54+F53 -> 769.90173 | G56: =G54+G53 -> 923.10715 | H56: =H54+H53 -> 1109.2967 | I56: =I54+I53 -> 1335.1898
A58: Net Worth | B58: 184 | C58: 213 | D58: 243 | E58: =D58+E36 -> 285.15458 | F58: =E58+F36 -> 337.26627 | G58: =F58+G36 -> 401.21445 | H58: =G58+H36 -> 479.24922 | I58: =H58+I36 -> 574.0653
A60: Total Liabilities & Net worth | B60: =SUM(B58,B56) -> 588 | C60: =SUM(C58,C56) -> 665 | D60: =SUM(D58,D56) -> 784 | E60: =E58+E56 -> 929.24 | F60: =F58+F56 -> 1107.168 | G60: =G58+G56 -> 1324.3216 | H60: =H58+H56 -> 1588.5459 | I60: =I58+I56 -> 1909.2551
A63: Cash Flows | C63: 2005 | D63: 2006 | E63: =D63+1 -> 2007 | F63: =E63+1 -> 2008 | G63: =F63+1 -> 2009 | H63: =G63+1 -> 2010 | I63: =H63+1 -> 2011
A64: Net Income | C64: =C36 -> 29 | D64: =D36 -> 30 | E64: =E36 -> 42.154578 | F64: =F36 -> 52.111689 | G64: =G36 -> 63.94818 | H64: =H36 -> 78.034769 | I64: =I36 -> 94.81608
A65: Depreciation Exp | C65: =C31 -> 25 | D65: =D31 -> 35 | E65: =E31 -> 38.36 | F65: =F31 -> 42.392 | G65: =G31 -> 47.2304 | H65: =H31 -> 53.03648 | I65: =I31 -> 60.003776
A66: Change in A/R | C66: =B40-C40 -> -44 | D66: =C40-D40 -> -33 | E66: =D40-E40 -> -52.8 | F66: =E40-F40 -> -63.36 | G66: =F40-G40 -> -76.032 | H66: =G40-H40 -> -91.2384 | I66: =H40-I40 -> -109.48608
A67: Change in Inventory | C67: =B41-C41 -> -35 | D67: =C41-D41 -> -101 | E67: =D41-E41 -> -75.8 | F67: =E41-F41 -> -90.96 | G67: =F41-G41 -> -109.152 | H67: =G41-H41 -> -130.9824 | I67: =H41-I41 -> -157.17888
A68: change in A/P | C68: =C49-B49 -> 6 | D68: =D49-C49 -> 78 | E68: =E49-D49 -> 24 | F68: =F49-E49 -> 28.8 | G68: =G49-F49 -> 34.56 | H68: =H49-G49 -> 41.472 | I68: =I49-H49 -> 49.7664
A69: change in accrued exp | C69: =C51-B51 -> 1 | D69: =D51-C51 -> 0 | E69: =E51-D51 -> 2.8 | F69: =F51-E51 -> 3.36 | G69: =G51-F51 -> 4.032 | H69: =H51-G51 -> 4.8384 | I69: =I51-H51 -> 5.80608
A70: CF from Operations | C70: =SUM(C64:C69) -> -18 | D70: =SUM(D64:D69) -> 9 | E70: =SUM(E64:E69) -> -21.285422 | F70: =SUM(F64:F69) -> -27.656311 | G70: =SUM(G64:G69) -> -35.41342 | H70: =SUM(H64:H69) -> -44.839151 | I70: =SUM(I64:I69) -> -56.272624
A72: CAPEX | C72: =B43-C43 -> -15 | D72: =C43-D43 -> -50 | E72: =D43-E43 -> -50.4 | F72: =E43-F43 -> -60.48 | G72: =F43-G43 -> -72.576 | H72: =G43-H43 -> -87.0912 | I72: =H43-I43 -> -104.50944
A73: CF From Investment | C73: =C72 -> -15 | D73: =D72 -> -50 | E73: =E72 -> -50.4 | F73: =F72 -> -60.48 | G73: =G72 -> -72.576 | H73: =H72 -> -87.0912 | I73: =I72 -> -104.50944
A75: change in LOC | C75: =C50-B50 -> 65 | D75: =D50-C50 -> 35 | E75: =E50-D50 -> 100.28542 | F75: =F50-E50 -> 117.65631 | G75: =G50-F50 -> 138.61342 | H75: =H50-G50 -> 163.87916 | I75: =I50-H50 -> 194.32064
A76: change in debt | C76: =C54-B54+C52-B52 -> -24 | D76: =D54-C54+D52-C52 -> -24 | E76: =E54-D54+E52-D52 -> -24 | F76: =F54-E54+F52-E52 -> -24 | G76: =G54-F54+G52-F52 -> -24 | H76: =H54-G54+H52-G52 -> -24 | I76: =I54-H54+I52-H52 -> -24
A77: CF from Financing | C77: =C76+C75 -> 41 | D77: =D76+D75 -> 11 | E77: =E76+E75 -> 76.285422 | F77: =F76+F75 -> 93.656311 | G77: =G76+G75 -> 114.61342 | H77: =H76+H75 -> 139.87916 | I77: =I76+I75 -> 170.32064
A79: Total Change in Cash | C79: =C77+C73+C70 -> 8 | D79: =D77+D73+D70 -> -30 | E79: =E77+E73+E70 -> 4.6 | F79: =F77+F73+F70 -> 5.5200002 | G79: =G77+G73+G70 -> 6.6240012 | H79: =H77+H73+H70 -> 7.9488049 | I79: =I77+I73+I70 -> 9.5385757
A80: Beginning Cash | C80: =B39 -> 45 | D80: =C39 -> 53 | E80: =D39 -> 23 | F80: =E39 -> 27.6 | G80: =F39 -> 33.12 | H80: =G39 -> 39.744 | I80: =H39 -> 47.6928
A81: Ending Cash | C81: =C80+C79 -> 53 | D81: =D80+D79 -> 23 | E81: =E80+E79 -> 27.6 | F81: =F80+F79 -> 33.12 | G81: =G80+G79 -> 39.744001 | H81: =H80+H79 -> 47.692805 | I81: =I80+I79 -> 57.231376
B85: 2004 | C85: 2005 | D85: 2006 | E85: 2007 | F85: =E85+1 -> 2008 | G85: =F85+1 -> 2009 | H85: =G85+1 -> 2010 | I85: =H85+1 -> 2011
A86: CAPEX | C86: =C43-B43 -> 15 | D86: =D43-C43 -> 50 | E86: =E43-D43 -> 50.4 | F86: =F43-E43 -> 60.48 | G86: =G43-F43 -> 72.576 | H86: =H43-G43 -> 87.0912 | I86: =I43-H43 -> 104.50944
A87: Depreciation | D87: =D65 -> 35 | E87: =D87+E86/E20 -> 38.36 | F87: =E87+F86/F20 -> 42.392 | G87: =F87+G86/G20 -> 47.2304 | H87: =G87+H86/H20 -> 53.03648 | I87: =H87+I86/I20 -> 60.003776
A90: ROIC = NOPAT / Invested Capital
A91: EBIT | B91: =B29-B30-B31 -> 48 | C91: =C29-C30-C31 -> 74 | D91: =D29-D30-D31 -> 77 | E91: =E29-E30-E31 -> 96.04 | F91: =F29-F30-F31 -> 118.888 | G91: =G29-G30-G31 -> 146.3056 | H91: =H29-H30-H31 -> 179.20672 | I91: =I29-I30-I31 -> 218.68806
A92: NOPAT = EBIT * (1- TaxRate) | B92: =B91*(1-(B35/B34)) -> 32 | C92: =C91*(1-(C35/C34)) -> 48.772727 | D92: =D91*(1-(D35/D34)) -> 50.217391 | E92: =E91*(1-(E35/E34)) -> 65.37863 | F92: =F91*(1-(F35/F34)) -> 78.903405 | G92: =G91*(1-(G35/G34)) -> 95.229167 | H92: =H91*(1-(H35/H34)) -> 114.88519 | I92: =I91*(1-(I35/I34)) -> 138.51737
A94: Invested Capital (Operating Method) | B94: =B40+B41-B49-B51+B43+B44 -> 494 | C94: =C40+C41-C49-C51+C43+C44 -> 556 | D94: =D40+D41-D49-D51+D43+D44 -> 627 | E94: =E40+E41-E49-E51+E43+E44 -> 740.84 | F94: =F40+F41-F49-F51+F43+F44 -> 881.088 | G94: =G40+G41-G49-G51+G43+G44 -> 1053.0256 | H94: =H40+H41-H49-H51+H43+H44 -> 1262.9907 | I94: =I40+I41-I49-I51+I43+I44 -> 1518.5889
A96: Invested Capital (Financing Method) | B96: =B50+B52+B54+B58-B39 -> 494 | C96: =C50+C52+C54+C58-C39 -> 556 | D96: =D50+D52+D54+D58-D39 -> 627 | E96: =E50+E52+E54+E58-E39 -> 740.84 | F96: =F50+F52+F54+F58-F39 -> 881.088 | G96: =G50+G52+G54+G58-G39 -> 1053.0256 | H96: =H50+H52+H54+H58-H39 -> 1262.9907 | I96: =I50+I52+I54+I58-I39 -> 1518.5889
A98: Taxes using IF | E98: =IF(E34<40,E7*E34,(IF(E34<60,(40*E7+(E34-40)*E8),(40*E7+20*E8+E9*(E34-60))))) -> 19.769719 | F98: =IF(F34<40,F7*F34,(IF(F34<60,(40*F7+(F34-40)*F8),(40*F7+20*F8+F9*(F34-60))))) -> 26.407793 | G98: =IF(G34<40,G7*G34,(IF(G34<60,(40*G7+(G34-40)*G8),(40*G7+20*G8+G9*(G34-60))))) -> 34.298787 | H98: =IF(H34<40,H7*H34,(IF(H34<60,(40*H7+(H34-40)*H8),(40*H7+20*H8+H9*(H34-60))))) -> 43.689846 | I98: =IF(I34<40,I7*I34,(IF(I34<60,(40*I7+(I34-40)*I8),(40*I7+20*I8+I9*(I34-60))))) -> 54.877387
A100: ROIC | B100: =B92/B96 -> 0.064777328 | C100: =C92/C96 -> 0.087720733 | D100: =D92/D96 -> 0.080091533 | E100: =E92/E96 -> 0.088249325 | F100: =F92/F96 -> 0.089552241 | G100: =G92/G96 -> 0.090433858 | H100: =H92/H96 -> 0.09096281 | I100: =I92/I96 -> 0.091214528
Q159: Assumes DPO = 9 days
Q160: DSO
M161: DSI | P161: =I50 -> 963.75495 | Q161: 23 | R161: 33 | S161: 43 | T161: 53 | U161: 63 | V161: 43 | Y161: z
N162: 55 | P162: 56 | Q162: 963.75495 | R162: 963.75495 | S162: 963.75495 | T162: 963.75495 | U162: 963.75495 | V162: 963.75495
N163: 60 | P163: 66 | Q163: 963.75495 | R163: 963.75495 | S163: 963.75495 | T163: 963.75495 | U163: 963.75495 | V163: 963.75495
N164: 65 | P164: 76 | Q164: 963.75495 | R164: 963.75495 | S164: 963.75495 | T164: 963.75495 | U164: 963.75495 | V164: 963.75495
N165: 70 | P165: 86 | Q165: 963.75495 | R165: 963.75495 | S165: 963.75495 | T165: 963.75495 | U165: 963.75495 | V165: 963.75495
N166: 76 | P166: 96 | Q166: 963.75495 | R166: 963.75495 | S166: 963.75495 | T166: 963.75495 | U166: 963.75495 | V166: 963.75495
Q169: LOC 2012
Q170: sales growth
P171: =I50 -> 963.75495 | Q171: 0.05 | R171: 0.1 | S171: 0.15 | T171: 0.2
M172: DPO | N172: 10 | P172: 10 | Q172: 963.75495 | R172: 963.75495 | S172: 963.75495 | T172: 963.75495
N173: 24 | P173: 24 | Q173: 963.75495 | R173: 963.75495 | S173: 963.75495 | T173: 963.75495
N174: 45 | P174: 45 | Q174: 963.75495 | R174: 963.75495 | S174: 963.75495 | T174: 963.75495
N175: 60 | P175: 25 | Q175: 963.75495 | R175: 963.75495 | S175: 963.75495 | T175: 963.75495
Q177: Profit 2012
Q178: sales growth
P179: =E36 -> 42.154578 | Q179: 0.05 | R179: 0.1 | S179: 0.15 | T179: 0.2
M180: DPO | N180: 10 | P180: 10 | Q180: 42.154578 | R180: 42.154578 | S180: 42.154578 | T180: 42.154578
N181: 24 | P181: 24 | Q181: 42.154578 | R181: 42.154578 | S181: 42.154578 | T181: 42.154578
N182: 45 | P182: 45 | Q182: 42.154578 | R182: 42.154578 | S182: 42.154578 | T182: 42.154578
...

Sheet Q2
A2: Sales Growth | B2: Always hard to predict
A3: COGS(net)/Sales | B3: Predicated on getting discounts
A4: Operating Expenses/Sales
A5: Tax/Net Income Before Tax (tax inc<$40k)
A6: Tax/Net Income Before Tax ($40k<tax inc<$60k)
A7: Tax/Net Income Before Tax (tax inc>$60k)
A8: Int Exp Loan
A9: Int Exp New LOC | B9: May vary depending on line
A10: Purchase Discount
A11: Cash
A12: DSO ((A/R)/(Sales/365)) | B12: Can this be improved?
A13: DSI ((Inv/(COGS/365)) | B13: Can this be improved?
A14: Gross PPE/Sales | B14: Excess capacity?
A15: DPO ((A/P)/(COGS/365))
A16: Accrued Exp/Sales
A17: Depreciation Useful Life | B17: Making an assumption that useful life will be much higher than hist.

Sheet Q3
A2: a) | B2: If the company wants to obtain purchase discounts, they will need > $350k in 2007.
A3: b) | B3: At the current trends, it will not be paid off. However, if you begin to slow growth, you may be able to limit the growth and even pay it down.
A4: c) | B4: Inventory and accounts receviable investments.

Sheet Q4
B1: DPO = 24 | C1: DPO = 9 | D1: % change
A2: 2011 LOC | B2: 997 | C2: 975 | D2: =C2/B2-1 -> -0.022066199
A4: 2011 NI | B4: 87 | C4: 142 | D4: =C4/B4-1 -> 0.63218391

Sheet Q5
B3: LOC
B4: 2007 | C4: 2008 | D4: 2009 | E4: 2010 | F4: 2011
A5: DPO=24 | B5: 349.78944 | C5: 467.94493 | D5: 607.44851 | E5: 772.7004 | F5: 968.98689
A6: DPO=9 | B6: 405.43313 | C6: 510.49661 | D6: 633.17476 | E6: 777.06978 | F6: 946.50798

Sheet Q6 a) & b)
A3: 1) | E3: Assumes DPO = 24 days
E4: DSO
A5: DSI | D5: 968.98683 | E5: 23 | F5: 33 | G5: 43 | H5: 53 | I5: 63 | J5: 43
B6: 55 | D6: 56 | E6: 331.11153 | F6: 507.2326 | G6: 683.35368 | H6: 859.47476 | I6: 1035.5958 | J6: 683.35372
B7: 60 | D7: 66 | E7: 473.92813 | F7: 650.04918 | G7: 826.17027 | H7: 1002.2914 | I7: 1178.5093 | J7: 826.17031
B8: 65 | D8: 76 | E8: 616.74472 | F8: 792.86577 | G8: 968.98685 | H8: 1145.172 | I8: 1321.4666 | J8: 968.9869
B9: 70 | D9: 86 | E9: 759.5613 | F9: 935.68236 | G9: 1111.8347 | H9: 1288.1293 | I9: 1464.4239 | J9: 1111.8348
B10: 76 | D10: 96 | E10: 902.37789 | F10: 1078.4989 | G10: 1254.792 | H10: 1431.0866 | I10: 1607.619 | J10: 1254.7921
A12: 2) | E12: Assumes DPO = 9 days
E13: DSO
A14: DSI | D14: =#REF! -> #REF! | E14: 23 | F14: 33 | G14: 43 | H14: 53 | I14: 63 | J14: 43
B15: 56 | D15: 56 | E15: 314.34528 | F15: 490.46635 | G15: 666.58744 | H15: 842.70852 | I15: 1018.8296 | J15: 666.58748
B16: 66 | D16: 66 | E16: 454.30555 | F16: 630.42661 | G16: 806.54769 | H16: 982.66878 | I16: 1158.7899 | J16: 806.54773
B17: 76 | D17: 76 | E17: 594.26581 | F17: 770.38686 | G17: 946.50795 | H17: 1122.629 | I17: 1298.7501 | J17: 946.50799
B18: 86 | D18: 86 | E18: 734.22607 | F18: 910.34712 | G18: 1086.4682 | H18: 1262.5893 | I18: 1438.7104 | J18: 1086.4682
B19: 96 | D19: 96 | E19: 874.18632 | F19: 1050.3074 | G19: 1226.4285 | H19: 1402.5495 | I19: 1578.6706 | J19: 1226.4285
J20: 1226.4285

Sheet Q6 c)
B2: Scenario Summary
D3: Current Values: | E3: Base | F3: Best | G3: Worst
E4: Created by John W Molloy on 9/24/2017 Modified by John W Molloy on 9/18/2018 | F4: Created by John W Molloy on 9/24/2017 | G4: Created by John W Molloy on 9/24/2017 Modified by John W Molloy on 9/18/2018
B5: Changing Cells:
C6: $E$5 | D6: 0.8109 | E6: 0.8109 | F6: 0.75 | G6: 0.85
C7: $E$14 | D7: 43 | E7: 43 | F7: 28 | G7: 68
C8: $E$15 | D8: 76 | E8: 76 | F8: 51 | G8: 101
B9: Result Cells:
C10: $I$50 | D10: 968.98683 | E10: 968.98683 | F10: 0 | G10: 2426.0132
B11: Notes: Current Values column represents values of changing cells at
B12: time Scenario Summary Report was created. Changing cells for each
B13: scenario are highlighted in gray.

Sheet ROIC
B1: 2004 | C1: 2005 | D1: 2006 | E1: 2007 | F1: =E1+1 -> 2008 | G1: =F1+1 -> 2009 | H1: =G1+1 -> 2010 | I1: =H1+1 -> 2011
A2: NOPAT | C2: ='ROIC supp'!C6 -> 49.4 | D2: ='ROIC supp'!D6 -> 51.2 | E2: ='ROIC supp'!E6 -> 62.624 | F2: ='ROIC supp'!F6 -> 76.3328 | G2: ='ROIC supp'!G6 -> 92.78336 | H2: ='ROIC supp'!H6 -> 112.52403 | I2: ='ROIC supp'!I6 -> 136.21284
A3: IC (avg) | C3: =('Jones Model'!C40+'Jones Model'!C41+'Jones Model'!C45-'Jones Model'!C49-'Jones Model'!C51+'Jones Model'!B40+'Jones Model'!B41+'Jones Model'!B45-'Jones Model'!B49-'Jones Model'!B51)/2 -> 525 | D3: =('Jones Model'!D40+'Jones Model'!D41+'Jones Model'!D45-'Jones Model'!D49-'Jones Model'!D51+'Jones Model'!C40+'Jones Model'!C41+'Jones Model'!C45-'Jones Model'!C49-'Jones Model'!C51)/2 -> 591.5 | E3: =('Jones Model'!E40+'Jones Model'!E41+'Jones Model'!E45-'Jones Model'!E49-'Jones Model'!E51+'Jones Model'!D40+'Jones Model'!D41+'Jones Model'!D45-'Jones Model'!D49-'Jones Model'!D51)/2 -> 683.92 | F3: =('Jones Model'!F40+'Jones Model'!F41+'Jones Model'!F45-'Jones Model'!F49-'Jones Model'!F51+'Jones Model'!E40+'Jones Model'!E41+'Jones Model'!E45-'Jones Model'!E49-'Jones Model'!E51)/2 -> 810.964 | G3: =('Jones Model'!G40+'Jones Model'!G41+'Jones Model'!G45-'Jones Model'!G49-'Jones Model'!G51+'Jones Model'!F40+'Jones Model'!F41+'Jones Model'!F45-'Jones Model'!F49-'Jones Model'!F51)/2 -> 967.0568 | H3: =('Jones Model'!H40+'Jones Model'!H41+'Jones Model'!H45-'Jones Model'!H49-'Jones Model'!H51+'Jones Model'!G40+'Jones Model'!G41+'Jones Model'!G45-'Jones Model'!G49-'Jones Model'!G51)/2 -> 1158.0082 | I3: =('Jones Model'!I40+'Jones Model'!I41+'Jones Model'!I45-'Jones Model'!I49-'Jones Model'!I51+'Jones Model'!H40+'Jones Model'!H41+'Jones Model'!H45-'Jones Model'!H49-'Jones Model'!H51)/2 -> 1390.7898
A4: ROIC | C4: =C2/C3 -> 0.094095238 | D4: =D2/D3 -> 0.086559594 | E4: =E2/E3 -> 0.091566265 | F4: =F2/F3 -> 0.094126003 | G4: =G2/G3 -> 0.095944065 | H4: =H2/H3 -> 0.097170327 | I4: =I2/I3 -> 0.097939199
A5: Invested Capial Turnover | C5: ='Jones Model'!C25/C3 -> 3.6495238 | D5: ='Jones Model'!D25/D3 -> 3.7903635 | E5: ='Jones Model'!E25/E3 -> 3.9337934 | F5: ='Jones Model'!F25/F3 -> 3.9810398 | G5: ='Jones Model'!G25/G3 -> 4.0061514 | H5: ='Jones Model'!H25/H3 -> 4.0146619 | I5: ='Jones Model'!I25/I3 -> 4.0112557
A6: After-tax operarting margin | C6: =C2/'Jones Model'!C25 -> 0.025782881 | D6: =D2/'Jones Model'!D25 -> 0.022836753 | E6: =E2/'Jones Model'!E25 -> 0.023276836 | F6: =F2/'Jones Model'!F25 -> 0.023643572 | G6: =G2/'Jones Model'!G25 -> 0.023949186 | H6: =H2/'Jones Model'!H25 -> 0.024203863 | I6: =I2/'Jones Model'!I25 -> 0.024416095
A7: Leverage Ratio | C7: ='Jones Model'!C47/'Jones Model'!C58 -> 3.1220657 | D7: ='Jones Model'!D47/'Jones Model'!D58 -> 3.2263374 | E7: ='Jones Model'!E47/'Jones Model'!E58 -> 3.2587238 | F7: ='Jones Model'!F47/'Jones Model'!F58 -> 3.2827712 | G7: ='Jones Model'!G47/'Jones Model'!G58 -> 3.3007824 | H7: ='Jones Model'!H47/'Jones Model'!H58 -> 3.3146552 | I7: ='Jones Model'!I47/'Jones Model'!I58 -> 3.3258501
A8: Return on Equity | C8: ='Jones Model'!C36/('Jones Model'!B58+'Jones Model'!C58)/2 -> 0.036523929 | D8: ='Jones Model'!D36/('Jones Model'!C58+'Jones Model'!D58)/2 -> 0.032894737 | E8: ='Jones Model'!E36/('Jones Model'!D58+'Jones Model'!E58)/2 -> 0.039907425 | F8: ='Jones Model'!F36/('Jones Model'!E58+'Jones Model'!F58)/2 -> 0.041862101 | G8: ='Jones Model'!G36/('Jones Model'!F58+'Jones Model'!G58)/2 -> 0.043297123 | H8: ='Jones Model'!H36/('Jones Model'!G58+'Jones Model'!H58)/2 -> 0.044314588 | I8: ='Jones Model'!I36/('Jones Model'!H58+'Jones Model'!I58)/2 -> 0.045008437

Sheet ROIC supp
B1: 2004 | C1: 2005 | D1: 2006 | E1: 2007 | F1: =E1+1 -> 2008 | G1: =F1+1 -> 2009 | H1: =G1+1 -> 2010 | I1: =H1+1 -> 2011
A2: Invested Capital | B2: ='Jones Model'!B40+'Jones Model'!B41+'Jones Model'!B43+'Jones Model'!B44-'Jones Model'!B49-'Jones Model'!B51 -> 494 | C2: ='Jones Model'!C40+'Jones Model'!C41+'Jones Model'!C43+'Jones Model'!C44-'Jones Model'!C49-'Jones Model'!C51 -> 556 | D2: ='Jones Model'!D40+'Jones Model'!D41+'Jones Model'!D43+'Jones Model'!D44-'Jones Model'!D49-'Jones Model'!D51 -> 627 | E2: ='Jones Model'!E40+'Jones Model'!E41+'Jones Model'!E43+'Jones Model'!E44-'Jones Model'!E49-'Jones Model'!E51 -> 740.84 | F2: ='Jones Model'!F40+'Jones Model'!F41+'Jones Model'!F43+'Jones Model'!F44-'Jones Model'!F49-'Jones Model'!F51 -> 881.088 | G2: ='Jones Model'!G40+'Jones Model'!G41+'Jones Model'!G43+'Jones Model'!G44-'Jones Model'!G49-'Jones Model'!G51 -> 1053.0256 | H2: ='Jones Model'!H40+'Jones Model'!H41+'Jones Model'!H43+'Jones Model'!H44-'Jones Model'!H49-'Jones Model'!H51 -> 1262.9907 | I2: ='Jones Model'!I40+'Jones Model'!I41+'Jones Model'!I43+'Jones Model'!I44-'Jones Model'!I49-'Jones Model'!I51 -> 1518.5889
A4: EBIT | B4: ='Jones Model'!B29-'Jones Model'!B30-'Jones Model'!B31 -> 48 | C4: ='Jones Model'!C29-'Jones Model'!C30-'Jones Model'!C31 -> 74 | D4: ='Jones Model'!D29-'Jones Model'!D30-'Jones Model'!D31 -> 77 | E4: ='Jones Model'!E29-'Jones Model'!E30-'Jones Model'!E31 -> 96.04 | F4: ='Jones Model'!F29-'Jones Model'!F30-'Jones Model'!F31 -> 118.888 | G4: ='Jones Model'!G29-'Jones Model'!G30-'Jones Model'!G31 -> 146.3056 | H4: ='Jones Model'!H29-'Jones Model'!H30-'Jones Model'!H31 -> 179.20672 | I4: ='Jones Model'!I29-'Jones Model'!I30-'Jones Model'!I31 -> 218.68806
A5: Tax | B5: =IF(B4<40,'Jones Model'!E7*B4,(IF(B4<60,(40*'Jones Model'!E7+(B4-40)*'Jones Model'!E8),(40*'Jones Model'!D7+20*'Jones Model'!E8+'Jones Model'!E9*(B4-60))))) -> 14.8 | C5: =IF(C4<40,'Jones Model'!E7*C4,(IF(C4<60,(40*'Jones Model'!E7+(C4-40)*'Jones Model'!E8),(40*'Jones Model'!E7+20*'Jones Model'!E8+'Jones Model'!E9*(C4-60))))) -> 24.6 | D5: =IF(D4<40,'Jones Model'!E7*D4,(IF(D4<60,(40*'Jones Model'!E7+(D4-40)*'Jones Model'!E8),(40*'Jones Model'!E7+20*'Jones Model'!E8+'Jones Model'!E9*(D4-60))))) -> 25.8 | E5: =IF(E4<40,'Jones Model'!E7*E4,(IF(E4<60,(40*'Jones Model'!E7+(E4-40)*'Jones Model'!E8),(40*'Jones Model'!E7+20*'Jones Model'!E8+'Jones Model'!E9*(E4-60))))) -> 33.416 | F5: =IF(F4<40,'Jones Model'!F7*F4,(IF(F4<60,(40*'Jones Model'!F7+(F4-40)*'Jones Model'!F8),(40*'Jones Model'!F7+20*'Jones Model'!F8+'Jones Model'!F9*(F4-60))))) -> 42.5552 | G5: =IF(G4<40,'Jones Model'!G7*G4,(IF(G4<60,(40*'Jones Model'!G7+(G4-40)*'Jones Model'!G8),(40*'Jones Model'!G7+20*'Jones Model'!G8+'Jones Model'!G9*(G4-60))))) -> 53.52224 | H5: =IF(H4<40,'Jones Model'!H7*H4,(IF(H4<60,(40*'Jones Model'!H7+(H4-40)*'Jones Model'!H8),(40*'Jones Model'!H7+20*'Jones Model'!H8+'Jones Model'!H9*(H4-60))))) -> 66.682688 | I5: =IF(I4<40,'Jones Model'!I7*I4,(IF(I4<60,(40*'Jones Model'!I7+(I4-40)*'Jones Model'!I8),(40*'Jones Model'!I7+20*'Jones Model'!I8+'Jones Model'!I9*(I4-60))))) -> 82.475226
A6: NOPAT | B6: =B4-B5 -> 33.2 | C6: =C4-C5 -> 49.4 | D6: =D4-D5 -> 51.2 | E6: =E4-E5 -> 62.624 | F6: =F4-F5 -> 76.3328 | G6: =G4-G5 -> 92.78336 | H6: =H4-H5 -> 112.52403 | I6: =I4-I5 -> 136.21284

Sheet Sheet3
B1: 2006 | C1: 2007 | D1: 2008 | E1: 2009 | F1: 2010 | G1: 2011
A2: Sales | C2: ='Jones Model'!E25 -> 2690.4 | D2: ='Jones Model'!F25 -> 3228.48 | E2: ='Jones Model'!G25 -> 3874.176 | F2: ='Jones Model'!H25 -> 4649.0112 | G2: ='Jones Model'!I25 -> 5578.8134
A4: EBIT | C4: ='Jones Model'!E29-'Jones Model'!E30-'Jones Model'!E31 -> 96.04 | D4: ='Jones Model'!F29-'Jones Model'!F30-'Jones Model'!F31 -> 118.888 | E4: ='Jones Model'!G29-'Jones Model'!G30-'Jones Model'!G31 -> 146.3056 | F4: ='Jones Model'!H29-'Jones Model'!H30-'Jones Model'!H31 -> 179.20672 | G4: ='Jones Model'!I29-'Jones Model'!I30-'Jones Model'!I31 -> 218.68806
A5: tax | C5: =C4*35% -> 33.614 | D5: =D4*35% -> 41.6108 | E5: =E4*35% -> 51.20696 | F5: =F4*35% -> 62.722352 | G5: =G4*35% -> 76.540822
A6: NOPAT | C6: =C4-C5 -> 62.426 | D6: =D4-D5 -> 77.2772 | E6: =E4-E5 -> 95.09864 | F6: =F4-F5 -> 116.48437 | G6: =G4-G5 -> 142.14724
A8: Invested Capital-Operating | B8: ='Jones Model'!D40+'Jones Model'!D41+'Jones Model'!D45-'Jones Model'!D49-'Jones Model'!D51 -> 627 | C8: ='Jones Model'!E40+'Jones Model'!E41+'Jones Model'!E45-'Jones Model'!E49-'Jones Model'!E51 -> 740.84 | D8: ='Jones Model'!F40+'Jones Model'!F41+'Jones Model'!F45-'Jones Model'!F49-'Jones Model'!F51 -> 881.088 | E8: ='Jones Model'!G40+'Jones Model'!G41+'Jones Model'!G45-'Jones Model'!G49-'Jones Model'!G51 -> 1053.0256 | F8: ='Jones Model'!H40+'Jones Model'!H41+'Jones Model'!H45-'Jones Model'!H49-'Jones Model'!H51 -> 1262.9907 | G8: ='Jones Model'!I40+'Jones Model'!I41+'Jones Model'!I45-'Jones Model'!I49-'Jones Model'!I51 -> 1518.5889
A9: Invested Capital-Financing | B9: ='Jones Model'!D50+'Jones Model'!D52+'Jones Model'!D54+'Jones Model'!D58-'Jones Model'!D39 -> 627 | C9: ='Jones Model'!E50+'Jones Model'!E52+'Jones Model'!E54+'Jones Model'!E58-'Jones Model'!E39 -> 740.84 | D9: ='Jones Model'!F50+'Jones Model'!F52+'Jones Model'!F54+'Jones Model'!F58-'Jones Model'!F39 -> 881.088 | E9: ='Jones Model'!G50+'Jones Model'!G52+'Jones Model'!G54+'Jones Model'!G58-'Jones Model'!G39 -> 1053.0256 | F9: ='Jones Model'!H50+'Jones Model'!H52+'Jones Model'!H54+'Jones Model'!H58-'Jones Model'!H39 -> 1262.9907 | G9: ='Jones Model'!I50+'Jones Model'!I52+'Jones Model'!I54+'Jones Model'!I58-'Jones Model'!I39 -> 1518.5889
A10: Average Invested Capital | C10: =(C8+B8)/2 -> 683.92 | D10: =(D8+C8)/2 -> 810.964 | E10: =(E8+D8)/2 -> 967.0568 | F10: =(F8+E8)/2 -> 1158.0082 | G10: =(G8+F8)/2 -> 1390.7898
A12: ROIC | C12: =C6/C10 -> 0.091276758 | D12: =D6/D10 -> 0.095290543 | E12: =E6/E10 -> 0.098338216 | F12: =F6/F10 -> 0.10059028 | G12: =G6/G10 -> 0.10220613
A14: After-tax Operating Margin | C14: =C6/C2 -> 0.023203241 | D14: =D6/D2 -> 0.023936094 | E14: =E6/E2 -> 0.024546804 | F14: =F6/F2 -> 0.02505573 | G14: =G6/G2 -> 0.025479834
A15: Invested Capital Turnover | C15: =C2/C10 -> 3.9337934 | D15: =D2/D10 -> 3.9810398 | E15: =E2/E10 -> 4.0061514 | F15: =F2/F10 -> 4.0146619 | G15: =G2/G10 -> 4.0112557
A16: ROIC | C16: =C15*C14 -> 0.091276758 | D16: =D15*D14 -> 0.095290543 | E16: =E15*E14 -> 0.098338216 | F16: =F15*F14 -> 0.10059028 | G16: =G15*G14 -> 0.10220613
A18: DSO | B18: 43
A19: DSI | B19: 76
A20: DPO | B20: 9
A21: Gross PPE%Sales | B21: 0.1124
A22: COGS%Sales | B22: 0.8174
A23: OpExp%Sales | B23: 0.13

Sheet Sheet2
B1: 2006 | C1: 2007 | D1: 2008 | E1: 2009 | F1: 2010 | G1: 2011
A2: Sales | C2: ='Jones Model'!E25 -> 2690.4 | D2: ='Jones Model'!F25 -> 3228.48 | E2: ='Jones Model'!G25 -> 3874.176 | F2: ='Jones Model'!H25 -> 4649.0112 | G2: ='Jones Model'!I25 -> 5578.8134
A4: EBIT | C4: ='Jones Model'!E29-'Jones Model'!E30-'Jones Model'!E31 -> 96.04 | D4: ='Jones Model'!F29-'Jones Model'!F30-'Jones Model'!F31 -> 118.888 | E4: ='Jones Model'!G29-'Jones Model'!G30-'Jones Model'!G31 -> 146.3056 | F4: ='Jones Model'!H29-'Jones Model'!H30-'Jones Model'!H31 -> 179.20672 | G4: ='Jones Model'!I29-'Jones Model'!I30-'Jones Model'!I31 -> 218.68806
A5: tax (.35) | C5: =C4*0.35 -> 33.614 | D5: =D4*0.35 -> 41.6108 | E5: =E4*0.35 -> 51.20696 | F5: =F4*0.35 -> 62.722352 | G5: =G4*0.35 -> 76.540822
A6: nopat | C6: =C4-C5 -> 62.426 | D6: =D4-D5 -> 77.2772 | E6: =E4-E5 -> 95.09864 | F6: =F4-F5 -> 116.48437 | G6: =G4-G5 -> 142.14724
A8: Invested Capital - OPERATING | B8: ='Jones Model'!D40+'Jones Model'!D41+'Jones Model'!D45-'Jones Model'!D49-'Jones Model'!D51 -> 627 | C8: ='Jones Model'!E40+'Jones Model'!E41+'Jones Model'!E45-'Jones Model'!E49-'Jones Model'!E51 -> 740.84 | D8: ='Jones Model'!F40+'Jones Model'!F41+'Jones Model'!F45-'Jones Model'!F49-'Jones Model'!F51 -> 881.088 | E8: ='Jones Model'!G40+'Jones Model'!G41+'Jones Model'!G45-'Jones Model'!G49-'Jones Model'!G51 -> 1053.0256 | F8: ='Jones Model'!H40+'Jones Model'!H41+'Jones Model'!H45-'Jones Model'!H49-'Jones Model'!H51 -> 1262.9907 | G8: ='Jones Model'!I40+'Jones Model'!I41+'Jones Model'!I45-'Jones Model'!I49-'Jones Model'!I51 -> 1518.5889
A9: Invested Capital - FINANCING | B9: ='Jones Model'!D50+'Jones Model'!D52+'Jones Model'!D54+'Jones Model'!D58-'Jones Model'!D39 -> 627 | C9: ='Jones Model'!E50+'Jones Model'!E52+'Jones Model'!E54+'Jones Model'!E58-'Jones Model'!E39 -> 740.84 | D9: ='Jones Model'!F50+'Jones Model'!F52+'Jones Model'!F54+'Jones Model'!F58-'Jones Model'!F39 -> 881.088 | E9: ='Jones Model'!G50+'Jones Model'!G52+'Jones Model'!G54+'Jones Model'!G58-'Jones Model'!G39 -> 1053.0256 | F9: ='Jones Model'!H50+'Jones Model'!H52+'Jones Model'!H54+'Jones Model'!H58-'Jones Model'!H39 -> 1262.9907 | G9: ='Jones Model'!I50+'Jones Model'!I52+'Jones Model'!I54+'Jones Model'!I58-'Jones Model'!I39 -> 1518.5889
A11: Average Invested Capital | C11: =(C9+B9)/2 -> 683.92 | D11: =(D9+C9)/2 -> 810.964 | E11: =(E9+D9)/2 -> 967.0568 | F11: =(F9+E9)/2 -> 1158.0082 | G11: =(G9+F9)/2 -> 1390.7898
A13: ROIC | C13: =C6/C11 -> 0.091276758 | D13: =D6/D11 -> 0.095290543 | E13: =E6/E11 -> 0.098338215 | F13: =F6/F11 -> 0.10059028 | G13: =G6/G11 -> 0.10220613
A15: After-tax Operating Margin | C15: =C6/C2 -> 0.023203241 | D15: =D6/D2 -> 0.023936094 | E15: =E6/E2 -> 0.024546804 | F15: =F6/F2 -> 0.02505573 | G15: =G6/G2 -> 0.025479834
A16: Invested Capital Turnover | C16: =C2/C11 -> 3.9337934 | D16: =D2/D11 -> 3.9810398 | E16: =E2/E11 -> 4.0061514 | F16: =F2/F11 -> 4.0146619 | G16: =G2/G11 -> 4.0112556
A17: ROIC | C17: =C16*C15 -> 0.091276758 | D17: =D16*D15 -> 0.095290543 | E17: =E16*E15 -> 0.098338215 | F17: =F16*F15 -> 0.10059028 | G17: =G16*G15 -> 0.10220613
A19: DSO | B19: 43
A20: DSI | B20: 76
A21: DPO | B21: 9
A22: COGS%Sales | B22: 0.8174
A23: OperExp%sales | B23: 0.14

Sheet Sheet1
B2: 2006 | C2: 2007 | D2: 2008 | E2: 2009 | F2: 2010 | G2: 2011
A3: Invested Capital - Operating | B3: ='Jones Model'!D40+'Jones Model'!D41+'Jones Model'!D45-'Jones Model'!D49-'Jones Model'!D51 -> 627 | C3: ='Jones Model'!E40+'Jones Model'!E41+'Jones Model'!E45-'Jones Model'!E49-'Jones Model'!E51 -> 740.84 | D3: ='Jones Model'!F40+'Jones Model'!F41+'Jones Model'!F45-'Jones Model'!F49-'Jones Model'!F51 -> 881.088 | E3: ='Jones Model'!G40+'Jones Model'!G41+'Jones Model'!G45-'Jones Model'!G49-'Jones Model'!G51 -> 1053.0256 | F3: ='Jones Model'!H40+'Jones Model'!H41+'Jones Model'!H45-'Jones Model'!H49-'Jones Model'!H51 -> 1262.9907 | G3: ='Jones Model'!I40+'Jones Model'!I41+'Jones Model'!I45-'Jones Model'!I49-'Jones Model'!I51 -> 1518.5889
A4: Invested Capital - Financial | B4: ='Jones Model'!D50+'Jones Model'!D52+'Jones Model'!D54+'Jones Model'!D58-'Jones Model'!D39 -> 627 | C4: ='Jones Model'!E50+'Jones Model'!E52+'Jones Model'!E54+'Jones Model'!E58-'Jones Model'!E39 -> 740.84 | D4: ='Jones Model'!F50+'Jones Model'!F52+'Jones Model'!F54+'Jones Model'!F58-'Jones Model'!F39 -> 881.088 | E4: ='Jones Model'!G50+'Jones Model'!G52+'Jones Model'!G54+'Jones Model'!G58-'Jones Model'!G39 -> 1053.0256 | F4: ='Jones Model'!H50+'Jones Model'!H52+'Jones Model'!H54+'Jones Model'!H58-'Jones Model'!H39 -> 1262.9907 | G4: ='Jones Model'!I50+'Jones Model'!I52+'Jones Model'!I54+'Jones Model'!I58-'Jones Model'!I39 -> 1518.5889
A5: Average Invested Capital | C5: =(C4+B4)/2 -> 683.92 | D5: =(D4+C4)/2 -> 810.964 | E5: =(E4+D4)/2 -> 967.0568 | F5: =(F4+E4)/2 -> 1158.0082 | G5: =(G4+F4)/2 -> 1390.7898
A6: EBIT | C6: ='Jones Model'!D29-'Jones Model'!D30-'Jones Model'!D31 -> 77 | D6: ='Jones Model'!E29-'Jones Model'!E30-'Jones Model'!E31 -> 96.04 | E6: ='Jones Model'!F29-'Jones Model'!F30-'Jones Model'!F31 -> 118.888 | F6: ='Jones Model'!G29-'Jones Model'!G30-'Jones Model'!G31 -> 146.3056 | G6: ='Jones Model'!H29-'Jones Model'!H30-'Jones Model'!H31 -> 179.20672
A7: tax | C7: 0.35 | D7: 0.35 | E7: 0.35 | F7: 0.35 | G7: 0.35
A8: NOPAT | C8: =C6*(1-C7) -> 50.05 | D8: =D6*(1-D7) -> 62.426 | E8: =E6*(1-E7) -> 77.2772 | F8: =F6*(1-F7) -> 95.09864 | G8: =G6*(1-G7) -> 116.48437
A10: Return on Invested Capital (ROIC) | C10: =C8/((B3+C3)/2) -> 0.073181074 | D10: =D8/((C3+D3)/2) -> 0.076977523 | E10: =E8/((D3+E3)/2) -> 0.079909681 | F10: =F8/((E3+F3)/2) -> 0.082122599 | G10: =G8/((F3+G3)/2) -> 0.083754115
A12: Sales | C12: ='Jones Model'!E25 -> 2690.4 | D12: ='Jones Model'!F25 -> 3228.48 | E12: ='Jones Model'!G25 -> 3874.176 | F12: ='Jones Model'!H25 -> 4649.0112 | G12: ='Jones Model'!I25 -> 5578.8134
A14: Invested Capital Turnover | C14: =C12/C5 -> 3.9337934 | D14: =D12/D5 -> 3.9810398 | E14: =E12/E5 -> 4.0061514 | F14: =F12/F5 -> 4.0146619 | G14: =G12/G5 -> 4.0112556
A16: After-tax Operating Margin | C16: =C8/C12 -> 0.018603182 | D16: =D8/D12 -> 0.019336034 | E16: =E8/E12 -> 0.019946745 | F16: =F8/F12 -> 0.02045567 | G16: =G8/G12 -> 0.020879775
A18: ROIC | C18: =C16*C14 -> 0.073181074 | D18: =D16*D14 -> 0.076977523 | E18: =E16*E14 -> 0.079909681 | F18: =F16*F14 -> 0.082122599 | G18: =G16*G14 -> 0.083754114

Sheet FCF
B1: 2006 | C1: 2007 | D1: =C1+1 -> 2008 | E1: =D1+1 -> 2009 | F1: =E1+1 -> 2010 | G1: =F1+1 -> 2011
A2: Gross Profit | B2: ='Jones Model'!D29 -> 424 | C2: ='Jones Model'!E29 -> 508.8 | D2: ='Jones Model'!F29 -> 610.56 | E2: ='Jones Model'!G29 -> 732.672 | F2: ='Jones Model'!H29 -> 879.2064 | G2: ='Jones Model'!I29 -> 1055.0477
A3: Less Operating Exp (Excl Depr) | B3: ='Jones Model'!D30+('Jones Model'!D44-'Jones Model'!C44) -> 277 | C3: ='Jones Model'!E30+('Jones Model'!E44-'Jones Model'!D44) -> 336.04 | D3: ='Jones Model'!F30+('Jones Model'!F44-'Jones Model'!E44) -> 406.888 | E3: ='Jones Model'!G30+('Jones Model'!G44-'Jones Model'!F44) -> 491.9056 | F3: ='Jones Model'!H30+('Jones Model'!H44-'Jones Model'!G44) -> 593.92672 | G3: ='Jones Model'!I30+('Jones Model'!I44-'Jones Model'!H44) -> 716.35206
A4: Less Depreciation | B4: =B22 -> 35 | C4: =C22 -> 38.36 | D4: =D22 -> 42.392 | E4: =E22 -> 47.2304 | F4: =F22 -> 53.03648 | G4: =G22 -> 60.003776
A5: EBIT | B5: =B2-B3-B4 -> 112 | C5: =C2-C3-C4 -> 134.4 | D5: =D2-D3-D4 -> 161.28 | E5: =E2-E3-E4 -> 193.536 | F5: =F2-F3-F4 -> 232.2432 | G5: =G2-G3-G4 -> 278.69184
A6: Less Taxes | C6: =C5*C21 -> 47.04 | D6: =D5*D21 -> 56.448 | E6: =E5*E21 -> 67.7376 | F6: =F5*F21 -> 81.28512 | G6: =G5*G21 -> 97.542144
A7: NOPAT | C7: =C5-C6 -> 87.36 | D7: =D5-D6 -> 104.832 | E7: =E5-E6 -> 125.7984 | F7: =F5-F6 -> 150.95808 | G7: =G5-G6 -> 181.1497
A8: Add Depreciation | C8: =C22 -> 38.36 | D8: =D22 -> 42.392 | E8: =E22 -> 47.2304 | F8: =F22 -> 53.03648 | G8: =G22 -> 60.003776
A9: Less CAPEX | C9: =C23 -> 50.4 | D9: =D23 -> 60.48 | E9: =E23 -> 72.576 | F9: =F23 -> 87.0912 | G9: =G23 -> 104.50944
A10: Less Change NWC | C10: =C30 -> 101.8 | D10: =D30 -> 122.16 | E10: =E30 -> 146.592 | F10: =F30 -> 175.9104 | G10: =G30 -> 211.09248
A11: FCF | C11: =C7+C8-C9-C10 -> -26.48 | D11: =D7+D8-D9-D10 -> -35.416 | E11: =E7+E8-E9-E10 -> -46.1392 | F11: =F7+F8-F9-F10 -> -59.00704 | G11: =G7+G8-G9-G10 -> -74.448448
A12: Terminal Value | F12: =G11/(B32-B31) -> -930.6056
A13: FCF + TV | C13: =SUM(C11:C12) -> -26.48 | D13: =SUM(D11:D12) -> -35.416 | E13: =SUM(E11:E12) -> -46.1392 | F13: =SUM(F11:F12) -> -989.61264
A14: Enterprise Value | B14: =NPV(B32,C13:F13) -> -763.92596
A15: Less Debt | B15: ='Jones Model'!D52+'Jones Model'!D54 -> 158
A16: Add Cash | B16: ='Jones Model'!D39 -> 23
A17: Equity Value | B17: =B14-B15+B16 -> -898.92596
A21: Taxes on EBIT | B21: 0.35 | C21: 0.35 | D21: 0.35 | E21: 0.35 | F21: 0.35 | G21: 0.35
A22: Depreciation | B22: =-('Jones Model'!D44-'Jones Model'!C44) -> 35 | C22: =-('Jones Model'!E44-'Jones Model'!D44) -> 38.36 | D22: =-('Jones Model'!F44-'Jones Model'!E44) -> 42.392 | E22: =-('Jones Model'!G44-'Jones Model'!F44) -> 47.2304 | F22: =-('Jones Model'!H44-'Jones Model'!G44) -> 53.03648 | G22: =-('Jones Model'!I44-'Jones Model'!H44) -> 60.003776
A23: CAPEX | B23: ='Jones Model'!D43-'Jones Model'!C43 -> 50 | C23: ='Jones Model'!E43-'Jones Model'!D43 -> 50.4 | D23: ='Jones Model'!F43-'Jones Model'!E43 -> 60.48 | E23: ='Jones Model'!G43-'Jones Model'!F43 -> 72.576 | F23: ='Jones Model'!H43-'Jones Model'!G43 -> 87.0912 | G23: ='Jones Model'!I43-'Jones Model'!H43 -> 104.50944
A24: NWC
A25: A/R | B25: ='Jones Model'!D40 -> 264 | C25: ='Jones Model'!E40 -> 316.8 | D25: ='Jones Model'!F40 -> 380.16 | E25: ='Jones Model'!G40 -> 456.192 | F25: ='Jones Model'!H40 -> 547.4304 | G25: ='Jones Model'!I40 -> 656.91648
A26: Inv | B26: ='Jones Model'!D41 -> 379 | C26: ='Jones Model'!E41 -> 454.8 | D26: ='Jones Model'!F41 -> 545.76 | E26: ='Jones Model'!G41 -> 654.912 | F26: ='Jones Model'!H41 -> 785.8944 | G26: ='Jones Model'!I41 -> 943.07328
A27: A/P | B27: ='Jones Model'!D49 -> 120 | C27: ='Jones Model'!E49 -> 144 | D27: ='Jones Model'!F49 -> 172.8 | E27: ='Jones Model'!G49 -> 207.36 | F27: ='Jones Model'!H49 -> 248.832 | G27: ='Jones Model'!I49 -> 298.5984
A28: Accured Exp | B28: ='Jones Model'!D51 -> 14 | C28: ='Jones Model'!E51 -> 16.8 | D28: ='Jones Model'!F51 -> 20.16 | E28: ='Jones Model'!G51 -> 24.192 | F28: ='Jones Model'!H51 -> 29.0304 | G28: ='Jones Model'!I51 -> 34.83648
A29: Total NWC | B29: =B25+B26-B27-B28 -> 509 | C29: =C25+C26-C27-C28 -> 610.8 | D29: =D25+D26-D27-D28 -> 732.96 | E29: =E25+E26-E27-E28 -> 879.552 | F29: =F25+F26-F27-F28 -> 1055.4624 | G29: =G25+G26-G27-G28 -> 1266.5549
A30: Change NWC | C30: =C29-B29 -> 101.8 | D30: =D29-C29 -> 122.16 | E30: =E29-D29 -> 146.592 | F30: =F29-E29 -> 175.9104 | G30: =G29-F29 -> 211.09248
A31: Terminal Value Growth Rate | B31: 0.02
A32: WACC | B32: 0.1

Sheet Balance Sheet
L2: recursive | M2: on
J18: D | K18: ='Jones Model'!D54+'Jones Model'!D52+'Jones Model'!D50 -> 407 | L18: =K18/K19 -> 1.6748971 | M18: ='Jones Model'!I50+'Jones Model'!I52+'Jones Model'!I54 -> 1001.7549 | N18: =M18/M19 -> 1.7450192
J19: E | K19: ='Jones Model'!D58 -> 243 | M19: ='Jones Model'!I58 -> 574.06527
K24: ='Jones Model'!I50 -> 963.75495 | L24: 0.05 | M24: 0.1 | N24: 0.15 | O24: 0.2 | P24: 0.25
K25: 10
K26: 25
A58: Purchases
A59: Beg Inv | C59: ='Jones Model'!B41 -> 243
A60: COGS | C60: ='Jones Model'!C26 -> 1566.3265
A61: Ending Inv | C61: ='Jones Model'!C41 -> 278
A62: Purchases | C62: =C59+C60-C61 -> 1531.3265
